[
  {
    "ticket": 84355954,
    "symbol": "USDJPY",
    "direction": "UNKNOWN",
    "structure_type": "unknown",
    "entry_time": "",
    "entry_price": 0.0,
    "sl": 0.0,
    "tp": 0.0,
    "volume": 0.02,
    "intended_rr": 0.0,
    "exit_time": "2025-12-17T22:00:09.373611+00:00",
    "exit_price": 155.654,
    "exit_reason": "unknown",
    "pnl_pips": 0.0,
    "pnl_usd": 0.13,
    "achieved_rr": 0.0,
    "hold_time_minutes": 0.0,
    "outcome": "win",
    "magic": 0,
    "comment": ""
  },
  {
    "ticket": 84332717,
    "symbol": "USDJPY",
    "direction": "UNKNOWN",
    "structure_type": "unknown",
    "entry_time": "",
    "entry_price": 0.0,
    "sl": 0.0,
    "tp": 0.0,
    "volume": 0.01,
    "intended_rr": 0.0,
    "exit_time": "2025-12-17T22:00:09.373611+00:00",
    "exit_price": 155.639,
    "exit_reason": "unknown",
    "pnl_pips": 0.0,
    "pnl_usd": 0.08,
    "achieved_rr": 0.0,
    "hold_time_minutes": 0.0,
    "outcome": "win",
    "magic": 0,
    "comment": ""
  },
  {
    "ticket": 84315981,
    "symbol": "GBPUSD",
    "direction": "UNKNOWN",
    "structure_type": "unknown",
    "entry_time": "",
    "entry_price": 0.0,
    "sl": 0.0,
    "tp": 0.0,
    "volume": 0.99,
    "intended_rr": 0.0,
    "exit_time": "2025-12-17T22:00:09.373611+00:00",
    "exit_price": 1.33744,
    "exit_reason": "unknown",
    "pnl_pips": 0.0,
    "pnl_usd": -149.49,
    "achieved_rr": 0.0,
    "hold_time_minutes": 0.0,
    "outcome": "loss",
    "magic": 0,
    "comment": ""
  },
  {
    "ticket": 84305090,
    "symbol": "GBPUSD",
    "direction": "UNKNOWN",
    "structure_type": "unknown",
    "entry_time": "",
    "entry_price": 0.0,
    "sl": 0.0,
    "tp": 0.0,
    "volume": 1.74,
    "intended_rr": 0.0,
    "exit_time": "2025-12-17T22:00:09.373611+00:00",
    "exit_price": 1.33742,
    "exit_reason": "unknown",
    "pnl_pips": 0.0,
    "pnl_usd": -219.24,
    "achieved_rr": 0.0,
    "hold_time_minutes": 0.0,
    "outcome": "loss",
    "magic": 0,
    "comment": ""
  },
  {
    "ticket": 84296669,
    "symbol": "GBPUSD",
    "direction": "UNKNOWN",
    "structure_type": "unknown",
    "entry_time": "",
    "entry_price": 0.0,
    "sl": 0.0,
    "tp": 0.0,
    "volume": 1.04,
    "intended_rr": 0.0,
    "exit_time": "2025-12-17T22:00:09.373611+00:00",
    "exit_price": 1.33741,
    "exit_reason": "unknown",
    "pnl_pips": 0.0,
    "pnl_usd": -165.36,
    "achieved_rr": 0.0,
    "hold_time_minutes": 0.0,
    "outcome": "loss",
    "magic": 0,
    "comment": ""
  },
  {
    "ticket": 84287708,
    "symbol": "GBPUSD",
    "direction": "UNKNOWN",
    "structure_type": "unknown",
    "entry_time": "",
    "entry_price": 0.0,
    "sl": 0.0,
    "tp": 0.0,
    "volume": 1.23,
    "intended_rr": 0.0,
    "exit_time": "2025-12-17T22:00:09.373611+00:00",
    "exit_price": 1.33741,
    "exit_reason": "unknown",
    "pnl_pips": 0.0,
    "pnl_usd": -217.71,
    "achieved_rr": 0.0,
    "hold_time_minutes": 0.0,
    "outcome": "loss",
    "magic": 0,
    "comment": ""
  },
  {
    "ticket": 84355950,
    "symbol": "EURUSD",
    "direction": "UNKNOWN",
    "structure_type": "unknown",
    "entry_time": "",
    "entry_price": 0.0,
    "sl": 0.0,
    "tp": 0.0,
    "volume": 5.65,
    "intended_rr": 0.0,
    "exit_time": "2025-12-17T22:00:09.373611+00:00",
    "exit_price": 1.17428,
    "exit_reason": "unknown",
    "pnl_pips": 0.0,
    "pnl_usd": 67.8,
    "achieved_rr": 0.0,
    "hold_time_minutes": 0.0,
    "outcome": "win",
    "magic": 0,
    "comment": ""
  },
  {
    "ticket": 84305085,
    "symbol": "EURUSD",
    "direction": "UNKNOWN",
    "structure_type": "unknown",
    "entry_time": "",
    "entry_price": 0.0,
    "sl": 0.0,
    "tp": 0.0,
    "volume": 1.97,
    "intended_rr": 0.0,
    "exit_time": "2025-12-17T22:00:09.373611+00:00",
    "exit_price": 1.17423,
    "exit_reason": "unknown",
    "pnl_pips": 0.0,
    "pnl_usd": -120.17,
    "achieved_rr": 0.0,
    "hold_time_minutes": 0.0,
    "outcome": "loss",
    "magic": 0,
    "comment": ""
  },
  {
    "ticket": 84265951,
    "symbol": "EURUSD",
    "direction": "UNKNOWN",
    "structure_type": "unknown",
    "entry_time": "",
    "entry_price": 0.0,
    "sl": 0.0,
    "tp": 0.0,
    "volume": 1.8900000000000001,
    "intended_rr": 0.0,
    "exit_time": "2025-12-17T22:00:09.373611+00:00",
    "exit_price": 1.17423,
    "exit_reason": "unknown",
    "pnl_pips": 0.0,
    "pnl_usd": -128.52,
    "achieved_rr": 0.0,
    "hold_time_minutes": 0.0,
    "outcome": "loss",
    "magic": 0,
    "comment": ""
  },
  {
    "ticket": 84287706,
    "symbol": "EURUSD",
    "direction": "UNKNOWN",
    "structure_type": "unknown",
    "entry_time": "",
    "entry_price": 0.0,
    "sl": 0.0,
    "tp": 0.0,
    "volume": 2.0,
    "intended_rr": 0.0,
    "exit_time": "2025-12-17T22:00:09.373611+00:00",
    "exit_price": 1.17423,
    "exit_reason": "unknown",
    "pnl_pips": 0.0,
    "pnl_usd": -166.0,
    "achieved_rr": 0.0,
    "hold_time_minutes": 0.0,
    "outcome": "loss",
    "magic": 0,
    "comment": ""
  }
]