{"timestamp": "2025-12-02T07:01:31.140915+00:00", "level": "INFO", "logger": "core.execution.mt5_executor", "message": "MT5Executor initialized in paper mode", "taskName": null}
{"timestamp": "2025-12-02T07:01:31.141272+00:00", "level": "INFO", "logger": "core.structure.detector", "message": "Initialized OrderBlockDetector", "taskName": null, "structure_type": "order_block", "enabled": true}
{"timestamp": "2025-12-02T07:01:31.141502+00:00", "level": "INFO", "logger": "core.structure.detector", "message": "Initialized FairValueGapDetector", "taskName": null, "structure_type": "fair_value_gap", "enabled": true}
{"timestamp": "2025-12-02T07:01:31.141885+00:00", "level": "INFO", "logger": "core.structure.detector", "message": "Initialized BreakOfStructureDetector", "taskName": null, "structure_type": "break_of_structure", "enabled": true}
{"timestamp": "2025-12-02T07:01:31.142087+00:00", "level": "INFO", "logger": "core.structure.detector", "message": "Initialized SweepDetector", "taskName": null, "structure_type": "sweep", "enabled": true}
{"timestamp": "2025-12-02T07:01:31.142278+00:00", "level": "INFO", "logger": "core.structure.detector", "message": "Initialized UnifiedZoneRejectionDetector", "taskName": null, "structure_type": "rejection", "enabled": true}
{"timestamp": "2025-12-02T07:01:31.142479+00:00", "level": "INFO", "logger": "core.structure.detector", "message": "Initialized EngulfingDetector", "taskName": null, "structure_type": "engulfing", "enabled": true}
{"timestamp": "2025-12-02T07:01:31.142658+00:00", "level": "INFO", "logger": "core.structure.manager", "message": "Initialized 6 detectors: ['OrderBlockDetector', 'FairValueGapDetector', 'BreakOfStructureDetector', 'SweepDetector', 'UnifiedZoneRejectionDetector', 'EngulfingDetector']", "taskName": null}
{"timestamp": "2025-12-02T07:01:31.143620+00:00", "level": "INFO", "logger": "core.orchestration.pipeline", "message": "broker_symbols_registered", "taskName": null, "registered": ["EURUSD", "GBPUSD", "USDJPY", "AUDUSD", "NZDUSD", "XAUUSD", "AUDJPY", "NVDA", "TSLA"]}
{"timestamp": "2025-12-02T07:01:31.160943+00:00", "level": "INFO", "logger": "__main__", "message": "live_session_start", "taskName": null, "executor_mode": "paper", "symbols": ["EURUSD"], "per_trade_pct": 0.005, "per_symbol_open_risk_cap_pct": 0.015}
{"timestamp": "2025-12-02T07:01:31.191072+00:00", "level": "INFO", "logger": "__main__", "message": "mt5_initialized", "taskName": null}
{"timestamp": "2025-12-02T10:30:02.245099+00:00", "level": "DEBUG", "logger": "core.structure.rejection", "message": "uzr_detected", "taskName": null, "direction": "bullish", "reaction_body_atr": 0.8220183486240649, "quality_score": 0.7233027522936097}
{"timestamp": "2025-12-02T10:30:02.245438+00:00", "level": "DEBUG", "logger": "core.structure.engulfing", "message": "engulfing_detected", "taskName": null, "structure_id": "a128b72ee5bfc76f", "direction": "bullish", "quality_score": 0.7822018348624065, "bar_index": 14}
{"timestamp": "2025-12-02T10:30:02.245684+00:00", "level": "DEBUG", "logger": "core.orchestration.pipeline", "message": "stage_5_decisions_generated", "taskName": null, "count": 2}
{"timestamp": "2025-12-02T10:30:02.245768+00:00", "level": "INFO", "logger": "core.orchestration.pipeline", "message": "decisions_deduplicated", "taskName": null, "symbol": "EURUSD", "original_count": 2, "kept_count": 1, "best_structure": "engulfing", "best_confidence": 0.7822018348624065}
{"timestamp": "2025-12-02T10:30:02.246240+00:00", "level": "INFO", "logger": "core.orchestration.pipeline", "message": "setup_rejected_tight_sl", "taskName": null, "session": null, "symbol": "EURUSD", "stop_distance_points": 9.999999999998899, "sl_hard_floor_points": 25.0, "reason": "sl_tighter_than_broker_minimum"}
{"timestamp": "2025-12-02T10:15:00+00:00", "level": "INFO", "logger": "core.orchestration.pipeline", "message": "session_counters", "taskName": null, "session": null, "decisions_attempted": 2, "decisions_accepted": 1}
{"timestamp": "2025-12-02T10:45:02.321506+00:00", "level": "DEBUG", "logger": "core.structure.sweep", "message": "sweep_detected", "taskName": null, "direction": "bearish", "quality_score": 0.6}
{"timestamp": "2025-12-02T10:45:02.321768+00:00", "level": "DEBUG", "logger": "core.structure.rejection", "message": "uzr_detected", "taskName": null, "direction": "bearish", "reaction_body_atr": 0.6654929577464437, "quality_score": 0.6998239436619665}
{"timestamp": "2025-12-02T10:45:02.321991+00:00", "level": "DEBUG", "logger": "core.orchestration.pipeline", "message": "stage_5_decisions_generated", "taskName": null, "count": 2}
{"timestamp": "2025-12-02T10:45:02.322067+00:00", "level": "INFO", "logger": "core.orchestration.pipeline", "message": "decisions_deduplicated", "taskName": null, "symbol": "EURUSD", "original_count": 2, "kept_count": 1, "best_structure": "rejection", "best_confidence": 0.6998239436619665}
{"timestamp": "2025-12-02T10:45:02.322401+00:00", "level": "INFO", "logger": "core.orchestration.pipeline", "message": "setup_rejected_tight_sl", "taskName": null, "session": null, "symbol": "EURUSD", "stop_distance_points": 9.999999999998899, "sl_hard_floor_points": 25.0, "reason": "sl_tighter_than_broker_minimum"}
{"timestamp": "2025-12-02T10:30:00+00:00", "level": "INFO", "logger": "core.orchestration.pipeline", "message": "session_counters", "taskName": null, "session": null, "decisions_attempted": 4, "decisions_accepted": 2}
{"timestamp": "2025-12-02T11:00:02.403775+00:00", "level": "DEBUG", "logger": "core.structure.rejection", "message": "uzr_detected", "taskName": null, "direction": "bearish", "reaction_body_atr": 0.39144736842103334, "quality_score": 0.658717105263155}
{"timestamp": "2025-12-02T11:00:02.403990+00:00", "level": "DEBUG", "logger": "core.orchestration.pipeline", "message": "stage_5_decisions_generated", "taskName": null, "count": 1}
{"timestamp": "2025-12-02T11:00:02.404122+00:00", "level": "INFO", "logger": "core.orchestration.pipeline", "message": "setup_rejected_tight_sl", "taskName": null, "session": null, "symbol": "EURUSD", "stop_distance_points": 9.999999999998899, "sl_hard_floor_points": 25.0, "reason": "sl_tighter_than_broker_minimum"}
{"timestamp": "2025-12-02T10:45:00+00:00", "level": "INFO", "logger": "core.orchestration.pipeline", "message": "session_counters", "taskName": null, "session": null, "decisions_attempted": 5, "decisions_accepted": 3}
{"timestamp": "2025-12-02T11:15:02.479054+00:00", "level": "DEBUG", "logger": "core.structure.rejection", "message": "uzr_detected", "taskName": null, "direction": "bullish", "reaction_body_atr": 0.6384364820846593, "quality_score": 0.6957654723126989}
{"timestamp": "2025-12-02T11:15:02.479287+00:00", "level": "DEBUG", "logger": "core.structure.engulfing", "message": "engulfing_detected", "taskName": null, "structure_id": "35e6ec2907f86803", "direction": "bullish", "quality_score": 0.763843648208466, "bar_index": 17}
{"timestamp": "2025-12-02T11:15:02.479488+00:00", "level": "DEBUG", "logger": "core.orchestration.pipeline", "message": "stage_5_decisions_generated", "taskName": null, "count": 2}
{"timestamp": "2025-12-02T11:15:02.479568+00:00", "level": "INFO", "logger": "core.orchestration.pipeline", "message": "decisions_deduplicated", "taskName": null, "symbol": "EURUSD", "original_count": 2, "kept_count": 1, "best_structure": "engulfing", "best_confidence": 0.763843648208466}
{"timestamp": "2025-12-02T11:15:02.480064+00:00", "level": "INFO", "logger": "core.orchestration.pipeline", "message": "setup_rejected_tight_sl", "taskName": null, "session": null, "symbol": "EURUSD", "stop_distance_points": 9.999999999998899, "sl_hard_floor_points": 25.0, "reason": "sl_tighter_than_broker_minimum"}
{"timestamp": "2025-12-02T11:00:00+00:00", "level": "INFO", "logger": "core.orchestration.pipeline", "message": "session_counters", "taskName": null, "session": null, "decisions_attempted": 7, "decisions_accepted": 4}
{"timestamp": "2025-12-02T11:45:02.630145+00:00", "level": "DEBUG", "logger": "core.structure.order_block", "message": "ob_detected", "taskName": null, "direction": "bearish", "quality_score": 0.6886877828054245}
{"timestamp": "2025-12-02T11:45:02.630413+00:00", "level": "DEBUG", "logger": "core.structure.break_of_structure", "message": "bos_detected", "taskName": null, "direction": "bearish", "quality_score": 0.65}
{"timestamp": "2025-12-02T11:45:02.630649+00:00", "level": "DEBUG", "logger": "core.structure.rejection", "message": "uzr_detected", "taskName": null, "direction": "bearish", "reaction_body_atr": 1.2669683257917788, "quality_score": 0.7900452488687668}
{"timestamp": "2025-12-02T11:45:02.630971+00:00", "level": "DEBUG", "logger": "core.orchestration.pipeline", "message": "stage_5_decisions_generated", "taskName": null, "count": 3}
{"timestamp": "2025-12-02T11:45:02.631045+00:00", "level": "INFO", "logger": "core.orchestration.pipeline", "message": "decisions_deduplicated", "taskName": null, "symbol": "EURUSD", "original_count": 3, "kept_count": 1, "best_structure": "rejection", "best_confidence": 0.7900452488687668}
{"timestamp": "2025-12-02T11:45:02.631405+00:00", "level": "INFO", "logger": "core.orchestration.pipeline", "message": "execution_sized", "taskName": null, "symbol": "EURUSD", "order_type": "SELL", "volume_rounded": 0.59, "risk": {"new_trade_risk": 49.56000000001026, "open_risk_before": 0.0, "cap_pct": 0.015, "equity": 10000.0, "stop_distance_points": 84.0000000000174, "volume_rounded": 0.59}, "risk_budget": 50.0, "cap_budget": 150.0, "session": null, "entry": 1.16068, "sl": 1.16152, "tp": 1.15942}
{"timestamp": "2025-12-02T11:45:02.631807+00:00", "level": "INFO", "logger": "core.execution.mt5_executor", "message": "order_send_attempt", "taskName": null, "symbol": "EURUSD", "type": "SELL", "volume": 0.59, "entry": 1.16068, "sl": 1.16152, "tp": 1.15942, "mode": "paper"}
{"timestamp": "2025-12-02T11:45:02.632139+00:00", "level": "INFO", "logger": "core.execution.mt5_executor", "message": "order_validation_passed", "taskName": null, "symbol": "EURUSD", "type": "SELL"}
{"timestamp": "2025-12-02T11:45:02.632456+00:00", "level": "INFO", "logger": "core.execution.mt5_executor", "message": "order_send_result", "taskName": null, "symbol": "EURUSD", "mode": "paper", "ticket": null, "retcode": "SIMULATED", "retcode_description": "Simulated send: MT5 order_send not invoked"}
{"timestamp": "2025-12-02T11:15:00+00:00", "level": "INFO", "logger": "core.orchestration.pipeline", "message": "session_counters", "taskName": null, "session": null, "decisions_attempted": 10, "decisions_accepted": 5}
{"timestamp": "2025-12-02T12:15:02.787752+00:00", "level": "DEBUG", "logger": "core.structure.rejection", "message": "uzr_detected", "taskName": null, "direction": "bullish", "reaction_body_atr": 1.6760563380280746, "quality_score": 0.8514084507042112}
{"timestamp": "2025-12-02T12:15:02.788021+00:00", "level": "DEBUG", "logger": "core.orchestration.pipeline", "message": "stage_5_decisions_generated", "taskName": null, "count": 1}
{"timestamp": "2025-12-02T12:15:02.788157+00:00", "level": "INFO", "logger": "core.orchestration.pipeline", "message": "setup_rejected_tight_sl", "taskName": null, "session": null, "symbol": "EURUSD", "stop_distance_points": 9.999999999998899, "sl_hard_floor_points": 25.0, "reason": "sl_tighter_than_broker_minimum"}
{"timestamp": "2025-12-02T11:45:00+00:00", "level": "INFO", "logger": "core.orchestration.pipeline", "message": "session_counters", "taskName": null, "session": null, "decisions_attempted": 11, "decisions_accepted": 6}
{"timestamp": "2025-12-02T12:30:02.865712+00:00", "level": "DEBUG", "logger": "core.structure.order_block", "message": "ob_detected", "taskName": null, "direction": "bearish", "quality_score": 0.828846153846145}
{"timestamp": "2025-12-02T12:30:02.865994+00:00", "level": "DEBUG", "logger": "core.structure.fair_value_gap", "message": "fvg_detected", "taskName": null, "direction": "bearish", "gap_size": 0.00038, "quality_score": 0.7023076923076884}
{"timestamp": "2025-12-02T12:30:02.866264+00:00", "level": "DEBUG", "logger": "core.structure.break_of_structure", "message": "bos_detected", "taskName": null, "direction": "bearish", "quality_score": 0.65}
{"timestamp": "2025-12-02T12:30:02.866884+00:00", "level": "DEBUG", "logger": "core.orchestration.pipeline", "message": "stage_5_decisions_generated", "taskName": null, "count": 3}
{"timestamp": "2025-12-02T12:30:02.867024+00:00", "level": "INFO", "logger": "core.orchestration.pipeline", "message": "decisions_deduplicated", "taskName": null, "symbol": "EURUSD", "original_count": 3, "kept_count": 1, "best_structure": "order_block", "best_confidence": 0.828846153846145}
{"timestamp": "2025-12-02T12:30:02.867416+00:00", "level": "INFO", "logger": "core.orchestration.pipeline", "message": "execution_sized", "taskName": null, "symbol": "EURUSD", "order_type": "SELL", "volume_rounded": 0.44, "risk": {"new_trade_risk": 49.8959999999986, "open_risk_before": 0.0, "cap_pct": 0.015, "equity": 10000.0, "stop_distance_points": 113.39999999999682, "volume_rounded": 0.44}, "risk_budget": 50.0, "cap_budget": 150.0, "session": null, "entry": 1.16024, "sl": 1.161374, "tp": 1.15816}
{"timestamp": "2025-12-02T12:30:02.867925+00:00", "level": "INFO", "logger": "core.execution.mt5_executor", "message": "order_send_attempt", "taskName": null, "symbol": "EURUSD", "type": "SELL", "volume": 0.44, "entry": 1.16024, "sl": 1.161374, "tp": 1.15816, "mode": "paper"}
{"timestamp": "2025-12-02T12:30:02.868289+00:00", "level": "INFO", "logger": "core.execution.mt5_executor", "message": "order_validation_passed", "taskName": null, "symbol": "EURUSD", "type": "SELL"}
{"timestamp": "2025-12-02T12:30:02.868616+00:00", "level": "INFO", "logger": "core.execution.mt5_executor", "message": "order_send_result", "taskName": null, "symbol": "EURUSD", "mode": "paper", "ticket": null, "retcode": "SIMULATED", "retcode_description": "Simulated send: MT5 order_send not invoked"}
{"timestamp": "2025-12-02T12:15:00+00:00", "level": "INFO", "logger": "core.orchestration.pipeline", "message": "session_counters", "taskName": null, "session": null, "decisions_attempted": 14, "decisions_accepted": 7}
{"timestamp": "2025-12-02T12:45:02.946955+00:00", "level": "DEBUG", "logger": "core.structure.sweep", "message": "sweep_detected", "taskName": null, "direction": "bullish", "quality_score": 0.6}
{"timestamp": "2025-12-02T12:45:02.947216+00:00", "level": "DEBUG", "logger": "core.structure.rejection", "message": "uzr_detected", "taskName": null, "direction": "bullish", "reaction_body_atr": 0.4138817480719741, "quality_score": 0.6620822622107961}
{"timestamp": "2025-12-02T12:45:02.947466+00:00", "level": "DEBUG", "logger": "core.orchestration.pipeline", "message": "stage_5_decisions_generated", "taskName": null, "count": 2}
{"timestamp": "2025-12-02T12:45:02.947641+00:00", "level": "INFO", "logger": "core.orchestration.pipeline", "message": "decisions_deduplicated", "taskName": null, "symbol": "EURUSD", "original_count": 2, "kept_count": 1, "best_structure": "rejection", "best_confidence": 0.6620822622107961}
{"timestamp": "2025-12-02T12:45:02.948037+00:00", "level": "INFO", "logger": "core.orchestration.pipeline", "message": "setup_rejected_tight_sl", "taskName": null, "session": null, "symbol": "EURUSD", "stop_distance_points": 9.999999999998899, "sl_hard_floor_points": 25.0, "reason": "sl_tighter_than_broker_minimum"}
{"timestamp": "2025-12-02T12:30:00+00:00", "level": "INFO", "logger": "core.orchestration.pipeline", "message": "session_counters", "taskName": null, "session": null, "decisions_attempted": 16, "decisions_accepted": 8}
{"timestamp": "2025-12-02T13:00:03.027039+00:00", "level": "DEBUG", "logger": "core.structure.fair_value_gap", "message": "fvg_detected", "taskName": null, "direction": "bullish", "gap_size": 5e-05, "quality_score": 0.613392857142857}
{"timestamp": "2025-12-02T13:00:03.027322+00:00", "level": "DEBUG", "logger": "core.orchestration.pipeline", "message": "stage_5_decisions_generated", "taskName": null, "count": 1}
{"timestamp": "2025-12-02T13:00:03.027455+00:00", "level": "INFO", "logger": "core.orchestration.pipeline", "message": "execution_sized", "taskName": null, "symbol": "EURUSD", "order_type": "BUY", "volume_rounded": 1.04, "risk": {"new_trade_risk": 49.92000000000373, "open_risk_before": 0.0, "cap_pct": 0.015, "equity": 10000.0, "stop_distance_points": 48.00000000000359, "volume_rounded": 1.04}, "risk_budget": 50.0, "cap_budget": 150.0, "session": null, "entry": 1.16066, "sl": 1.16018, "tp": 1.16138}
{"timestamp": "2025-12-02T13:00:03.027878+00:00", "level": "INFO", "logger": "core.execution.mt5_executor", "message": "order_send_attempt", "taskName": null, "symbol": "EURUSD", "type": "BUY", "volume": 1.04, "entry": 1.16066, "sl": 1.16018, "tp": 1.16138, "mode": "paper"}
{"timestamp": "2025-12-02T13:00:03.028146+00:00", "level": "INFO", "logger": "core.execution.mt5_executor", "message": "order_validation_passed", "taskName": null, "symbol": "EURUSD", "type": "BUY"}
{"timestamp": "2025-12-02T13:00:03.028466+00:00", "level": "INFO", "logger": "core.execution.mt5_executor", "message": "order_send_result", "taskName": null, "symbol": "EURUSD", "mode": "paper", "ticket": null, "retcode": "SIMULATED", "retcode_description": "Simulated send: MT5 order_send not invoked"}
{"timestamp": "2025-12-02T12:45:00+00:00", "level": "INFO", "logger": "core.orchestration.pipeline", "message": "session_counters", "taskName": null, "session": null, "decisions_attempted": 17, "decisions_accepted": 9}
{"timestamp": "2025-12-02T13:30:03.178272+00:00", "level": "DEBUG", "logger": "core.structure.break_of_structure", "message": "bos_detected", "taskName": null, "direction": "bullish", "quality_score": 0.65}
{"timestamp": "2025-12-02T13:30:03.178536+00:00", "level": "DEBUG", "logger": "core.structure.rejection", "message": "uzr_detected", "taskName": null, "direction": "bullish", "reaction_body_atr": 0.36793692509855935, "quality_score": 0.655190538764784}
{"timestamp": "2025-12-02T13:30:03.178891+00:00", "level": "DEBUG", "logger": "core.orchestration.pipeline", "message": "stage_5_decisions_generated", "taskName": null, "count": 2}
{"timestamp": "2025-12-02T13:30:03.178995+00:00", "level": "INFO", "logger": "core.orchestration.pipeline", "message": "decisions_deduplicated", "taskName": null, "symbol": "EURUSD", "original_count": 2, "kept_count": 1, "best_structure": "rejection", "best_confidence": 0.655190538764784}
{"timestamp": "2025-12-02T13:30:03.179321+00:00", "level": "INFO", "logger": "core.orchestration.pipeline", "message": "setup_rejected_tight_sl", "taskName": null, "session": null, "symbol": "EURUSD", "stop_distance_points": 9.999999999998899, "sl_hard_floor_points": 25.0, "reason": "sl_tighter_than_broker_minimum"}
{"timestamp": "2025-12-02T13:15:00+00:00", "level": "INFO", "logger": "core.orchestration.pipeline", "message": "session_counters", "taskName": null, "session": null, "decisions_attempted": 19, "decisions_accepted": 10}
{"timestamp": "2025-12-02T13:45:03.259972+00:00", "level": "DEBUG", "logger": "core.structure.break_of_structure", "message": "bos_detected", "taskName": null, "direction": "bullish", "quality_score": 0.65}
{"timestamp": "2025-12-02T13:45:03.260236+00:00", "level": "DEBUG", "logger": "core.orchestration.pipeline", "message": "stage_5_decisions_generated", "taskName": null, "count": 1}
{"timestamp": "2025-12-02T13:45:03.260366+00:00", "level": "INFO", "logger": "core.orchestration.pipeline", "message": "setup_rejected_tight_sl", "taskName": null, "session": null, "symbol": "EURUSD", "stop_distance_points": 9.999999999998899, "sl_hard_floor_points": 25.0, "reason": "sl_tighter_than_broker_minimum"}
{"timestamp": "2025-12-02T13:30:00+00:00", "level": "INFO", "logger": "core.orchestration.pipeline", "message": "session_counters", "taskName": null, "session": null, "decisions_attempted": 20, "decisions_accepted": 11}
{"timestamp": "2025-12-02T14:00:03.336412+00:00", "level": "DEBUG", "logger": "core.structure.break_of_structure", "message": "bos_detected", "taskName": null, "direction": "bullish", "quality_score": 0.65}
{"timestamp": "2025-12-02T14:00:03.336671+00:00", "level": "DEBUG", "logger": "core.structure.rejection", "message": "uzr_detected", "taskName": null, "direction": "bullish", "reaction_body_atr": 0.46728971962617444, "quality_score": 0.6700934579439262}
{"timestamp": "2025-12-02T14:00:03.336896+00:00", "level": "DEBUG", "logger": "core.orchestration.pipeline", "message": "stage_5_decisions_generated", "taskName": null, "count": 2}
{"timestamp": "2025-12-02T14:00:03.336977+00:00", "level": "INFO", "logger": "core.orchestration.pipeline", "message": "decisions_deduplicated", "taskName": null, "symbol": "EURUSD", "original_count": 2, "kept_count": 1, "best_structure": "rejection", "best_confidence": 0.6700934579439262}
{"timestamp": "2025-12-02T14:00:03.337345+00:00", "level": "INFO", "logger": "core.orchestration.pipeline", "message": "setup_rejected_tight_sl", "taskName": null, "session": null, "symbol": "EURUSD", "stop_distance_points": 9.999999999998899, "sl_hard_floor_points": 25.0, "reason": "sl_tighter_than_broker_minimum"}
{"timestamp": "2025-12-02T13:45:00+00:00", "level": "INFO", "logger": "core.orchestration.pipeline", "message": "session_counters", "taskName": null, "session": null, "decisions_attempted": 22, "decisions_accepted": 12}
{"timestamp": "2025-12-02T14:15:03.409325+00:00", "level": "DEBUG", "logger": "core.structure.rejection", "message": "uzr_detected", "taskName": null, "direction": "bearish", "reaction_body_atr": 0.631147540983424, "quality_score": 0.6946721311475136}
{"timestamp": "2025-12-02T14:15:03.409510+00:00", "level": "DEBUG", "logger": "core.structure.engulfing", "message": "engulfing_detected", "taskName": null, "structure_id": "2ca61725c3dd66d4", "direction": "bearish", "quality_score": 0.7631147540983424, "bar_index": 27}
{"timestamp": "2025-12-02T14:15:03.409701+00:00", "level": "DEBUG", "logger": "core.orchestration.pipeline", "message": "stage_5_decisions_generated", "taskName": null, "count": 2}
{"timestamp": "2025-12-02T14:15:03.409807+00:00", "level": "INFO", "logger": "core.orchestration.pipeline", "message": "decisions_deduplicated", "taskName": null, "symbol": "EURUSD", "original_count": 2, "kept_count": 1, "best_structure": "engulfing", "best_confidence": 0.7631147540983424}
{"timestamp": "2025-12-02T14:15:03.410184+00:00", "level": "INFO", "logger": "core.orchestration.pipeline", "message": "setup_rejected_tight_sl", "taskName": null, "session": null, "symbol": "EURUSD", "stop_distance_points": 9.999999999998899, "sl_hard_floor_points": 25.0, "reason": "sl_tighter_than_broker_minimum"}
{"timestamp": "2025-12-02T14:00:00+00:00", "level": "INFO", "logger": "core.orchestration.pipeline", "message": "session_counters", "taskName": null, "session": null, "decisions_attempted": 24, "decisions_accepted": 13}
{"timestamp": "2025-12-02T14:30:03.480672+00:00", "level": "DEBUG", "logger": "core.structure.order_block", "message": "ob_detected", "taskName": null, "direction": "bullish", "quality_score": 0.6930201342281598}
{"timestamp": "2025-12-02T14:30:03.480901+00:00", "level": "DEBUG", "logger": "core.structure.break_of_structure", "message": "bos_detected", "taskName": null, "direction": "bullish", "quality_score": 0.65}
{"timestamp": "2025-12-02T14:30:03.481033+00:00", "level": "DEBUG", "logger": "core.structure.sweep", "message": "sweep_detected", "taskName": null, "direction": "bullish", "quality_score": 0.6}
{"timestamp": "2025-12-02T14:30:03.481157+00:00", "level": "DEBUG", "logger": "core.structure.rejection", "message": "uzr_detected", "taskName": null, "direction": "bullish", "reaction_body_atr": 0.9583892617449664, "quality_score": 0.743758389261745}
{"timestamp": "2025-12-02T14:30:03.481276+00:00", "level": "DEBUG", "logger": "core.structure.engulfing", "message": "engulfing_detected", "taskName": null, "structure_id": "e68fa5c9f1255299", "direction": "bullish", "quality_score": 0.7958389261744967, "bar_index": 28}
{"timestamp": "2025-12-02T14:30:03.481627+00:00", "level": "DEBUG", "logger": "core.orchestration.pipeline", "message": "stage_5_decisions_generated", "taskName": null, "count": 5}
{"timestamp": "2025-12-02T14:30:03.481703+00:00", "level": "INFO", "logger": "core.orchestration.pipeline", "message": "decisions_deduplicated", "taskName": null, "symbol": "EURUSD", "original_count": 5, "kept_count": 1, "best_structure": "engulfing", "best_confidence": 0.7958389261744967}
{"timestamp": "2025-12-02T14:30:03.482078+00:00", "level": "INFO", "logger": "core.orchestration.pipeline", "message": "execution_sized", "taskName": null, "symbol": "EURUSD", "order_type": "BUY", "volume_rounded": 0.71, "risk": {"new_trade_risk": 49.70000000001029, "open_risk_before": 0.0, "cap_pct": 0.015, "equity": 10000.0, "stop_distance_points": 70.0000000000145, "volume_rounded": 0.71}, "risk_budget": 50.0, "cap_budget": 150.0, "session": null, "entry": 1.16134, "sl": 1.16064, "tp": 1.16239}
{"timestamp": "2025-12-02T14:30:03.482383+00:00", "level": "INFO", "logger": "core.execution.mt5_executor", "message": "order_send_attempt", "taskName": null, "symbol": "EURUSD", "type": "BUY", "volume": 0.71, "entry": 1.16134, "sl": 1.16064, "tp": 1.16239, "mode": "paper"}
{"timestamp": "2025-12-02T14:30:03.482638+00:00", "level": "INFO", "logger": "core.execution.mt5_executor", "message": "order_validation_passed", "taskName": null, "symbol": "EURUSD", "type": "BUY"}
{"timestamp": "2025-12-02T14:30:03.482956+00:00", "level": "INFO", "logger": "core.execution.mt5_executor", "message": "order_send_result", "taskName": null, "symbol": "EURUSD", "mode": "paper", "ticket": null, "retcode": "SIMULATED", "retcode_description": "Simulated send: MT5 order_send not invoked"}
{"timestamp": "2025-12-02T14:15:00+00:00", "level": "INFO", "logger": "core.orchestration.pipeline", "message": "session_counters", "taskName": null, "session": null, "decisions_attempted": 29, "decisions_accepted": 14}
{"timestamp": "2025-12-02T14:45:03.605079+00:00", "level": "DEBUG", "logger": "core.structure.break_of_structure", "message": "bos_detected", "taskName": null, "direction": "bullish", "quality_score": 0.65}
{"timestamp": "2025-12-02T14:45:03.605311+00:00", "level": "DEBUG", "logger": "core.structure.rejection", "message": "uzr_detected", "taskName": null, "direction": "bullish", "reaction_body_atr": 0.5953360768175583, "quality_score": 0.6893004115226338}
{"timestamp": "2025-12-02T14:45:03.605533+00:00", "level": "DEBUG", "logger": "core.orchestration.pipeline", "message": "stage_5_decisions_generated", "taskName": null, "count": 2}
{"timestamp": "2025-12-02T14:45:03.605610+00:00", "level": "INFO", "logger": "core.orchestration.pipeline", "message": "decisions_deduplicated", "taskName": null, "symbol": "EURUSD", "original_count": 2, "kept_count": 1, "best_structure": "rejection", "best_confidence": 0.6893004115226338}
{"timestamp": "2025-12-02T14:45:03.605936+00:00", "level": "INFO", "logger": "core.orchestration.pipeline", "message": "setup_rejected_tight_sl", "taskName": null, "session": null, "symbol": "EURUSD", "stop_distance_points": 9.999999999998899, "sl_hard_floor_points": 25.0, "reason": "sl_tighter_than_broker_minimum"}
{"timestamp": "2025-12-02T14:30:00+00:00", "level": "INFO", "logger": "core.orchestration.pipeline", "message": "session_counters", "taskName": null, "session": null, "decisions_attempted": 31, "decisions_accepted": 15}
{"timestamp": "2025-12-02T15:00:03.683239+00:00", "level": "DEBUG", "logger": "core.structure.order_block", "message": "ob_detected", "taskName": null, "direction": "bullish", "quality_score": 0.6926031294452347}
{"timestamp": "2025-12-02T15:00:03.683484+00:00", "level": "DEBUG", "logger": "core.structure.fair_value_gap", "message": "fvg_detected", "taskName": null, "direction": "bullish", "gap_size": 0.0002099999999999, "quality_score": 0.6627311522048065}
{"timestamp": "2025-12-02T15:00:03.683624+00:00", "level": "DEBUG", "logger": "core.structure.break_of_structure", "message": "bos_detected", "taskName": null, "direction": "bullish", "quality_score": 0.65}
{"timestamp": "2025-12-02T15:00:03.683980+00:00", "level": "DEBUG", "logger": "core.orchestration.pipeline", "message": "stage_5_decisions_generated", "taskName": null, "count": 3}
{"timestamp": "2025-12-02T15:00:03.684100+00:00", "level": "INFO", "logger": "core.orchestration.pipeline", "message": "decisions_deduplicated", "taskName": null, "symbol": "EURUSD", "original_count": 3, "kept_count": 1, "best_structure": "order_block", "best_confidence": 0.6926031294452347}
{"timestamp": "2025-12-02T15:00:03.684451+00:00", "level": "INFO", "logger": "core.orchestration.pipeline", "message": "execution_sized", "taskName": null, "symbol": "EURUSD", "order_type": "BUY", "volume_rounded": 0.79, "risk": {"new_trade_risk": 49.76999999999276, "open_risk_before": 0.0, "cap_pct": 0.015, "equity": 10000.0, "stop_distance_points": 62.999999999990834, "volume_rounded": 0.79}, "risk_budget": 50.0, "cap_budget": 150.0, "session": null, "entry": 1.16177, "sl": 1.16114, "tp": 1.16272}
{"timestamp": "2025-12-02T15:00:03.684920+00:00", "level": "INFO", "logger": "core.execution.mt5_executor", "message": "order_send_attempt", "taskName": null, "symbol": "EURUSD", "type": "BUY", "volume": 0.79, "entry": 1.16177, "sl": 1.16114, "tp": 1.16272, "mode": "paper"}
{"timestamp": "2025-12-02T15:00:03.685218+00:00", "level": "INFO", "logger": "core.execution.mt5_executor", "message": "order_validation_passed", "taskName": null, "symbol": "EURUSD", "type": "BUY"}
{"timestamp": "2025-12-02T15:00:03.685521+00:00", "level": "INFO", "logger": "core.execution.mt5_executor", "message": "order_send_result", "taskName": null, "symbol": "EURUSD", "mode": "paper", "ticket": null, "retcode": "SIMULATED", "retcode_description": "Simulated send: MT5 order_send not invoked"}
{"timestamp": "2025-12-02T14:45:00+00:00", "level": "INFO", "logger": "core.orchestration.pipeline", "message": "session_counters", "taskName": null, "session": null, "decisions_attempted": 34, "decisions_accepted": 16}
{"timestamp": "2025-12-02T15:30:03.836813+00:00", "level": "DEBUG", "logger": "core.structure.rejection", "message": "uzr_detected", "taskName": null, "direction": "bearish", "reaction_body_atr": 0.773371104815875, "quality_score": 0.7160056657223812}
{"timestamp": "2025-12-02T15:30:03.837057+00:00", "level": "DEBUG", "logger": "core.structure.engulfing", "message": "engulfing_detected", "taskName": null, "structure_id": "e4ef6c19d1c50689", "direction": "bearish", "quality_score": 0.7773371104815875, "bar_index": 32}
{"timestamp": "2025-12-02T15:30:03.837363+00:00", "level": "DEBUG", "logger": "core.orchestration.pipeline", "message": "stage_5_decisions_generated", "taskName": null, "count": 2}
{"timestamp": "2025-12-02T15:30:03.837507+00:00", "level": "INFO", "logger": "core.orchestration.pipeline", "message": "decisions_deduplicated", "taskName": null, "symbol": "EURUSD", "original_count": 2, "kept_count": 1, "best_structure": "engulfing", "best_confidence": 0.7773371104815875}
{"timestamp": "2025-12-02T15:30:03.837904+00:00", "level": "INFO", "logger": "core.orchestration.pipeline", "message": "setup_rejected_tight_sl", "taskName": null, "session": null, "symbol": "EURUSD", "stop_distance_points": 9.999999999998899, "sl_hard_floor_points": 25.0, "reason": "sl_tighter_than_broker_minimum"}
{"timestamp": "2025-12-02T15:15:00+00:00", "level": "INFO", "logger": "core.orchestration.pipeline", "message": "session_counters", "taskName": null, "session": null, "decisions_attempted": 36, "decisions_accepted": 17}
{"timestamp": "2025-12-02T15:45:03.916075+00:00", "level": "DEBUG", "logger": "core.structure.sweep", "message": "sweep_detected", "taskName": null, "direction": "bullish", "quality_score": 0.6}
{"timestamp": "2025-12-02T15:45:03.916338+00:00", "level": "DEBUG", "logger": "core.orchestration.pipeline", "message": "stage_5_decisions_generated", "taskName": null, "count": 1}
{"timestamp": "2025-12-02T15:45:03.916467+00:00", "level": "INFO", "logger": "core.orchestration.pipeline", "message": "setup_rejected_tight_sl", "taskName": null, "session": null, "symbol": "EURUSD", "stop_distance_points": 9.999999999998899, "sl_hard_floor_points": 25.0, "reason": "sl_tighter_than_broker_minimum"}
{"timestamp": "2025-12-02T15:30:00+00:00", "level": "INFO", "logger": "core.orchestration.pipeline", "message": "session_counters", "taskName": null, "session": null, "decisions_attempted": 37, "decisions_accepted": 18}
{"timestamp": "2025-12-02T17:00:04.274577+00:00", "level": "DEBUG", "logger": "core.structure.sweep", "message": "sweep_detected", "taskName": null, "direction": "bullish", "quality_score": 0.6}
{"timestamp": "2025-12-02T17:00:04.275000+00:00", "level": "DEBUG", "logger": "core.orchestration.pipeline", "message": "stage_5_decisions_generated", "taskName": null, "count": 1}
{"timestamp": "2025-12-02T17:00:04.275172+00:00", "level": "INFO", "logger": "core.orchestration.pipeline", "message": "setup_rejected_tight_sl", "taskName": null, "session": null, "symbol": "EURUSD", "stop_distance_points": 9.999999999998899, "sl_hard_floor_points": 25.0, "reason": "sl_tighter_than_broker_minimum"}
{"timestamp": "2025-12-02T16:45:00+00:00", "level": "INFO", "logger": "core.orchestration.pipeline", "message": "session_counters", "taskName": null, "session": null, "decisions_attempted": 38, "decisions_accepted": 19}
{"timestamp": "2025-12-02T17:15:04.352515+00:00", "level": "DEBUG", "logger": "core.structure.break_of_structure", "message": "bos_detected", "taskName": null, "direction": "bearish", "quality_score": 0.65}
{"timestamp": "2025-12-02T17:15:04.352774+00:00", "level": "DEBUG", "logger": "core.structure.rejection", "message": "uzr_detected", "taskName": null, "direction": "bearish", "reaction_body_atr": 2.177033492822773, "quality_score": 0.9265550239234159}
{"timestamp": "2025-12-02T17:15:04.353152+00:00", "level": "DEBUG", "logger": "core.orchestration.pipeline", "message": "stage_5_decisions_generated", "taskName": null, "count": 2}
{"timestamp": "2025-12-02T17:15:04.353235+00:00", "level": "INFO", "logger": "core.orchestration.pipeline", "message": "decisions_deduplicated", "taskName": null, "symbol": "EURUSD", "original_count": 2, "kept_count": 1, "best_structure": "rejection", "best_confidence": 0.9265550239234159}
{"timestamp": "2025-12-02T17:15:04.353550+00:00", "level": "INFO", "logger": "core.orchestration.pipeline", "message": "setup_rejected_tight_sl", "taskName": null, "session": null, "symbol": "EURUSD", "stop_distance_points": 9.999999999998899, "sl_hard_floor_points": 25.0, "reason": "sl_tighter_than_broker_minimum"}
{"timestamp": "2025-12-02T17:00:00+00:00", "level": "INFO", "logger": "core.orchestration.pipeline", "message": "session_counters", "taskName": null, "session": null, "decisions_attempted": 40, "decisions_accepted": 20}
{"timestamp": "2025-12-02T17:30:04.428821+00:00", "level": "DEBUG", "logger": "core.structure.order_block", "message": "ob_detected", "taskName": null, "direction": "bearish", "quality_score": 0.9043478260869298}
{"timestamp": "2025-12-02T17:30:04.429064+00:00", "level": "DEBUG", "logger": "core.structure.fair_value_gap", "message": "fvg_detected", "taskName": null, "direction": "bearish", "gap_size": 0.00074, "quality_score": 0.7732441471571887}
{"timestamp": "2025-12-02T17:30:04.429211+00:00", "level": "DEBUG", "logger": "core.structure.break_of_structure", "message": "bos_detected", "taskName": null, "direction": "bearish", "quality_score": 0.65}
{"timestamp": "2025-12-02T17:30:04.429375+00:00", "level": "DEBUG", "logger": "core.structure.rejection", "message": "uzr_detected", "taskName": null, "direction": "bearish", "reaction_body_atr": 1.0769230769230649, "quality_score": 0.7615384615384597}
{"timestamp": "2025-12-02T17:30:04.429734+00:00", "level": "DEBUG", "logger": "core.orchestration.pipeline", "message": "stage_5_decisions_generated", "taskName": null, "count": 4}
{"timestamp": "2025-12-02T17:30:04.429807+00:00", "level": "INFO", "logger": "core.orchestration.pipeline", "message": "decisions_deduplicated", "taskName": null, "symbol": "EURUSD", "original_count": 4, "kept_count": 1, "best_structure": "order_block", "best_confidence": 0.9043478260869298}
{"timestamp": "2025-12-02T17:30:04.430164+00:00", "level": "INFO", "logger": "core.orchestration.pipeline", "message": "execution_sized", "taskName": null, "symbol": "EURUSD", "order_type": "SELL", "volume_rounded": 0.21, "risk": {"new_trade_risk": 48.57300000000019, "open_risk_before": 0.0, "cap_pct": 0.015, "equity": 10000.0, "stop_distance_points": 231.30000000000092, "volume_rounded": 0.21}, "risk_budget": 50.0, "cap_budget": 150.0, "session": null, "entry": 1.15979, "sl": 1.162103, "tp": 1.15493}
{"timestamp": "2025-12-02T17:30:04.430583+00:00", "level": "INFO", "logger": "core.execution.mt5_executor", "message": "order_send_attempt", "taskName": null, "symbol": "EURUSD", "type": "SELL", "volume": 0.21, "entry": 1.15979, "sl": 1.162103, "tp": 1.15493, "mode": "paper"}
{"timestamp": "2025-12-02T17:30:04.430826+00:00", "level": "INFO", "logger": "core.execution.mt5_executor", "message": "order_validation_passed", "taskName": null, "symbol": "EURUSD", "type": "SELL"}
{"timestamp": "2025-12-02T17:30:04.431107+00:00", "level": "INFO", "logger": "core.execution.mt5_executor", "message": "order_send_result", "taskName": null, "symbol": "EURUSD", "mode": "paper", "ticket": null, "retcode": "SIMULATED", "retcode_description": "Simulated send: MT5 order_send not invoked"}
{"timestamp": "2025-12-02T17:15:00+00:00", "level": "INFO", "logger": "core.orchestration.pipeline", "message": "session_counters", "taskName": null, "session": null, "decisions_attempted": 44, "decisions_accepted": 21}
{"timestamp": "2025-12-02T17:45:04.508951+00:00", "level": "DEBUG", "logger": "core.structure.rejection", "message": "uzr_detected", "taskName": null, "direction": "bullish", "reaction_body_atr": 0.785433070866134, "quality_score": 0.7178149606299201}
{"timestamp": "2025-12-02T17:45:04.509310+00:00", "level": "DEBUG", "logger": "core.orchestration.pipeline", "message": "stage_5_decisions_generated", "taskName": null, "count": 1}
{"timestamp": "2025-12-02T17:45:04.509499+00:00", "level": "INFO", "logger": "core.orchestration.pipeline", "message": "setup_rejected_tight_sl", "taskName": null, "session": null, "symbol": "EURUSD", "stop_distance_points": 11.000000000005448, "sl_hard_floor_points": 25.0, "reason": "sl_tighter_than_broker_minimum"}
{"timestamp": "2025-12-02T17:30:00+00:00", "level": "INFO", "logger": "core.orchestration.pipeline", "message": "session_counters", "taskName": null, "session": null, "decisions_attempted": 45, "decisions_accepted": 22}
{"timestamp": "2025-12-02T18:00:04.588247+00:00", "level": "DEBUG", "logger": "core.structure.rejection", "message": "uzr_detected", "taskName": null, "direction": "bearish", "reaction_body_atr": 0.5811320754716981, "quality_score": 0.6871698113207547}
{"timestamp": "2025-12-02T18:00:04.588571+00:00", "level": "DEBUG", "logger": "core.orchestration.pipeline", "message": "stage_5_decisions_generated", "taskName": null, "count": 1}
{"timestamp": "2025-12-02T18:00:04.588691+00:00", "level": "INFO", "logger": "core.orchestration.pipeline", "message": "setup_rejected_tight_sl", "taskName": null, "session": null, "symbol": "EURUSD", "stop_distance_points": 11.000000000005448, "sl_hard_floor_points": 25.0, "reason": "sl_tighter_than_broker_minimum"}
{"timestamp": "2025-12-02T17:45:00+00:00", "level": "INFO", "logger": "core.orchestration.pipeline", "message": "session_counters", "taskName": null, "session": null, "decisions_attempted": 46, "decisions_accepted": 23}
{"timestamp": "2025-12-02T18:10:00.021678+00:00", "level": "INFO", "logger": "core.orchestration.pipeline", "message": "dry_run_exit_summary", "taskName": null, "exit_method_hist": {"order_block": 11, "fair_value_gap": 1, "atr": 27, "legacy": 7}, "rr_gate": {"overall_ge_1_5_pct": 95.65217391304348, "by_method": {"order_block": 100.0, "fair_value_gap": 100.0, "atr": 100.0, "legacy": 71.42857142857143}}}
